quantile_glasses/__init__.py
quantile_glasses/exceptions.py
quantile_glasses/linear.py
quantile_glasses-0.1.dist-info/METADATA
quantile_glasses-0.1.dist-info/WHEEL
quantile_glasses-0.1.dist-info/licenses/LICENSE
quantile_glasses-0.1.dist-info/RECORD
