Metadata-Version: 2.3
Name: quantile-glasses
Version: 0.1
Summary: A simple python package to correct the issue of quantile crossing in probabilistic forecasting
Project-URL: Homepage, https://github.com/edu230991/pyenerginet
Project-URL: Issues, https://github.com/edu230991/pyenerginet/issues
Author-email: Edoardo Simioni <edu230991@gmail.com>
License-File: LICENSE
Classifier: Operating System :: OS Independent
Classifier: Programming Language :: Python :: 3
Requires-Python: >=3.9
Requires-Dist: cvxpy<1.5,>=1.4.2
Requires-Dist: numpy<1.27,>=1.26.4
Requires-Dist: pandas<2.3,>=2.2.1
